dedupe/variables/__init__.py
dedupe/variables/frequency.py
dedupe/variables/gender.py
dedupe/variables/name.py
dedupe/variables/person.py
dedupe_variable_person-0.0.2.dist-info/DESCRIPTION.rst
dedupe_variable_person-0.0.2.dist-info/METADATA
dedupe_variable_person-0.0.2.dist-info/RECORD
dedupe_variable_person-0.0.2.dist-info/WHEEL
dedupe_variable_person-0.0.2.dist-info/metadata.json
dedupe_variable_person-0.0.2.dist-info/top_level.txt
