Metadata-Version: 2.0
Name: dedupe-variable-person
Version: 0.0.2
Summary: Variable type for American Person Names
Home-page: https://github.com/datamade/dedupe-variables-person
Author: UNKNOWN
Author-email: UNKNOWN
License: The MIT License: http://www.opensource.org/licenses/mit-license.php
Platform: UNKNOWN
Requires-Dist: dedupe-variable-name
